trnbl/__init__.py
trnbl/py.typed
trnbl/training_interval.py
trnbl/training_manager.py
trnbl/loggers/__init__.py
trnbl/loggers/base.py
trnbl/loggers/multi.py
trnbl/loggers/tensorboard.py
trnbl/loggers/wandb.py
trnbl/loggers/local/__init__.py
trnbl/loggers/local/build_dist.py
trnbl/loggers/local/html_frontend.py
trnbl/loggers/local/locallogger.py
trnbl/loggers/local/start_server.py
trnbl/loggers/local/frontend_src/dashboard.js
trnbl/loggers/local/frontend_src/favicon.png
trnbl/loggers/local/frontend_src/index_src.html
trnbl/loggers/local/frontend_src/style.css
trnbl-0.1.1.dist-info/METADATA
trnbl-0.1.1.dist-info/WHEEL
trnbl-0.1.1.dist-info/licenses/LICENSE
trnbl-0.1.1.dist-info/RECORD
