Metadata-Version: 2.4
Name: trnbl
Version: 0.1.1
Summary: training manager and loggers
Project-URL: Homepage, https://miv.name/trnbl
Project-URL: Documentation, https://miv.name/trnbl
Project-URL: Repository, https://github.com/mivanit/trnbl
Project-URL: Issues, https://github.com/mivanit/trnbl/issues
License-File: LICENSE
Classifier: License :: OSI Approved :: GNU General Public License v3 (GPLv3)
Classifier: Operating System :: OS Independent
Classifier: Programming Language :: Python :: 3.10
Classifier: Programming Language :: Python :: 3.11
Classifier: Programming Language :: Python :: 3.12
Classifier: Programming Language :: Python :: 3.13
Requires-Python: >=3.10
Requires-Dist: muutils>=0.6.21
Requires-Dist: pyyaml>=6.0.1
Requires-Dist: tomli>=2.2.1; python_version < '3.11'
Requires-Dist: tqdm>=4.66.4
Provides-Extra: monitoring
Requires-Dist: gputil>=1.4.0; extra == 'monitoring'
Requires-Dist: psutil>=5.9.8; extra == 'monitoring'
Provides-Extra: tensorboard
Requires-Dist: numpy>=1.12.0; extra == 'tensorboard'
Requires-Dist: tensorboard>=2.17.0; extra == 'tensorboard'
Provides-Extra: wandb
Requires-Dist: wandb>=0.16.6; extra == 'wandb'
